sentry_mongo/__init__.py
sentry_mongo/__main__.py
sentry_mongo/integrations.py
mongodb_sentry_integration-1.0.1.dist-info/LICENSE
mongodb_sentry_integration-1.0.1.dist-info/METADATA
mongodb_sentry_integration-1.0.1.dist-info/WHEEL
mongodb_sentry_integration-1.0.1.dist-info/top_level.txt
mongodb_sentry_integration-1.0.1.dist-info/RECORD
