Metadata-Version: 2.1
Name: mongodb-sentry-integration
Version: 1.0.1
Summary: A integration of MongoDB for the Sentry's Python SDK
Home-page: https://github.com/JoeVictor22/mongo_integration_sentry_python_sdk
Author: Joel Castro
Author-email: joelvictor1746@gmail.com
License: MIT
Classifier: License :: OSI Approved :: MIT License
License-File: LICENSE
Requires-Dist: sentry-sdk
Requires-Dist: pymongo (==3.*)
